Metadata-Version: 2.1
Name: th2-grpc-act-uiframework-web-demo
Version: 3.3.0.dev8505676661
Summary: th2_grpc_act_uiframework_web_demo
Home-page: https://github.com/th2-net/th2-grpc-act-uiframework-web-demo
Author: TH2-devs
Author-email: th2-devs@exactprosystems.com
License: Apache License 2.0
Platform: UNKNOWN
Requires-Python: >=3.7
